newpyter/ContentsManager.py
newpyter/__init__.py
newpyter/__main__.py
newpyter/config.py
newpyter/parsing.py
newpyter/utils.py
newpyter/newpyviewer/__init__.py
newpyter/newpyviewer/newpyviewer.py
newpyter/storage/__init__.py
newpyter-0.6.0.dist-info/METADATA
newpyter-0.6.0.dist-info/WHEEL
newpyter-0.6.0.dist-info/entry_points.txt
newpyter-0.6.0.dist-info/RECORD
